LICENSE
MANIFEST.in
README.rst
config.json
django_management.py
setup.cfg
app/__init__.py
app/admin.py
app/apps.py
app/models.py
app/tests.py
app/urls.py
app/views.py
app/docusign/__init__.py
app/docusign/apis/__init__.py
app/docusign/apis/accounts_api.py
app/docusign/apis/authentication_api.py
app/docusign/apis/billing_api.py
app/docusign/apis/bulk_envelopes_api.py
app/docusign/apis/cloud_storage_api.py
app/docusign/apis/comments_api.py
app/docusign/apis/connect_api.py
app/docusign/apis/custom_tabs_api.py
app/docusign/apis/data_feed_api.py
app/docusign/apis/diagnostics_api.py
app/docusign/apis/email_archive_api.py
app/docusign/apis/envelopes_api.py
app/docusign/apis/folders_api.py
app/docusign/apis/groups_api.py
app/docusign/apis/notary_api.py
app/docusign/apis/organizations_api.py
app/docusign/apis/power_forms_api.py
app/docusign/apis/signing_groups_api.py
app/docusign/apis/templates_api.py
app/docusign/apis/users_api.py
app/docusign/apis/workspaces_api.py
app/docusign/client/__init__.py
app/docusign/client/api_client.py
app/docusign/client/api_exception.py
app/docusign/client/api_response.py
app/docusign/client/configuration.py
app/docusign/client/auth/__init__.py
app/docusign/client/auth/oauth.py
app/docusign/models/__init__.py
app/docusign/models/access_code_format.py
app/docusign/models/account_address.py
app/docusign/models/account_billing_plan.py
app/docusign/models/account_billing_plan_response.py
app/docusign/models/account_identity_input_option.py
app/docusign/models/account_identity_verification_response.py
app/docusign/models/account_identity_verification_step.py
app/docusign/models/account_identity_verification_workflow.py
app/docusign/models/account_information.py
app/docusign/models/account_minimum_password_length.py
app/docusign/models/account_notification.py
app/docusign/models/account_password_expire_password_days.py
app/docusign/models/account_password_lockout_duration_minutes.py
app/docusign/models/account_password_lockout_duration_type.py
deligence_django_docusign_connect.egg-info/PKG-INFO
deligence_django_docusign_connect.egg-info/SOURCES.txt
deligence_django_docusign_connect.egg-info/dependency_links.txt
deligence_django_docusign_connect.egg-info/requires.txt
deligence_django_docusign_connect.egg-info/top_level.txt
deligence_django_docusign_connect-2.0.dist-info/LICENSE
deligence_django_docusign_connect-2.0.dist-info/METADATA
deligence_django_docusign_connect-2.0.dist-info/WHEEL
deligence_django_docusign_connect-2.0.dist-info/top_level.txt
deligence_django_docusign_connect-2.0.dist-info/RECORD
